matchescu/adt/__init__.py
matchescu/adt/entity_resolution_result.py
matchescu/data/__init__.py
matchescu/data/__pycache__/__init__.cpython-312.pyc
matchescu/data/__pycache__/_record.cpython-312.pyc
matchescu/data/_record.py
matchescu/py.typed
matchescu/similarity/__init__.py
matchescu/similarity/__pycache__/__init__.cpython-312.pyc
matchescu/similarity/__pycache__/_matcher.cpython-312.pyc
matchescu/similarity/__pycache__/_persistence.cpython-312.pyc
matchescu/similarity/__pycache__/_reference_graph.cpython-312.pyc
matchescu/similarity/_matcher.py
matchescu/similarity/_persistence.py
matchescu/similarity/_reference_graph.py
matchescu/typing/__init__.py
matchescu/typing/__pycache__/__init__.cpython-312.pyc
matchescu/typing/__pycache__/_data.cpython-312.pyc
matchescu/typing/__pycache__/_references.cpython-312.pyc
matchescu/typing/_data.py
matchescu/typing/_references.py
matchescu_base-0.22.1.dist-info/LICENSE
matchescu_base-0.22.1.dist-info/METADATA
matchescu_base-0.22.1.dist-info/WHEEL
matchescu_base-0.22.1.dist-info/RECORD
