Metadata-Version: 2.3
Name: matchescu-base
Version: 0.22.1
Summary: Base abstract data types for Entity Resolution
Author: Andrei Olar
Author-email: andrei.olar@ubbcluj.ro
Requires-Python: >=3.11,<4.0
Classifier: Programming Language :: Python :: 3
Classifier: Programming Language :: Python :: 3.11
Classifier: Programming Language :: Python :: 3.12
Classifier: Programming Language :: Python :: 3.13
Requires-Dist: networkx (>=3.4.2,<4.0.0)
